html_compose/__init__.py
html_compose/base_attribute.py
html_compose/base_element.py
html_compose/base_types.py
html_compose/cli.py
html_compose/custom_element.py
html_compose/document.py
html_compose/notebook.py
html_compose/py.typed
html_compose/translate_html.py
html_compose/util_funcs.py
html_compose/attributes/__init__.py
html_compose/attributes/a_attrs.py
html_compose/attributes/abbr_attrs.py
html_compose/attributes/area_attrs.py
html_compose/attributes/audio_attrs.py
html_compose/attributes/base_attrs.py
html_compose/attributes/bdo_attrs.py
html_compose/attributes/blockquote_attrs.py
html_compose/attributes/body_attrs.py
html_compose/attributes/button_attrs.py
html_compose/attributes/canvas_attrs.py
html_compose/attributes/col_attrs.py
html_compose/attributes/colgroup_attrs.py
html_compose/attributes/data_attrs.py
html_compose/attributes/del_attrs.py
html_compose/attributes/details_attrs.py
html_compose/attributes/dfn_attrs.py
html_compose/attributes/dialog_attrs.py
html_compose/attributes/embed_attrs.py
html_compose/attributes/fieldset_attrs.py
html_compose/attributes/form_attrs.py
html_compose/attributes/global_attrs.py
html_compose/attributes/iframe_attrs.py
html_compose/attributes/img_attrs.py
html_compose/attributes/input_attrs.py
html_compose/attributes/ins_attrs.py
html_compose/attributes/label_attrs.py
html_compose/attributes/li_attrs.py
html_compose/attributes/link_attrs.py
html_compose/attributes/map_attrs.py
html_compose/attributes/meta_attrs.py
html_compose/attributes/meter_attrs.py
html_compose/attributes/object_attrs.py
html_compose/attributes/ol_attrs.py
html_compose/attributes/optgroup_attrs.py
html_compose/attributes/option_attrs.py
html_compose/attributes/output_attrs.py
html_compose/attributes/progress_attrs.py
html_compose/attributes/q_attrs.py
html_compose/attributes/script_attrs.py
html_compose/attributes/select_attrs.py
html_compose/attributes/slot_attrs.py
html_compose/attributes/source_attrs.py
html_compose/attributes/style_attrs.py
html_compose-0.11.1.dist-info/METADATA
html_compose-0.11.1.dist-info/WHEEL
html_compose-0.11.1.dist-info/entry_points.txt
html_compose-0.11.1.dist-info/licenses/LICENSE.txt
html_compose-0.11.1.dist-info/RECORD
