Metadata-Version: 2.3
Name: html-compose
Version: 0.11.1
Summary: Composable HTML generation in python
Author-email: jealouscloud <github@noaha.org>
License: MIT
Classifier: Development Status :: 4 - Beta
Classifier: Environment :: Web Environment
Classifier: Intended Audience :: Developers
Classifier: Intended Audience :: Information Technology
Classifier: Intended Audience :: System Administrators
Classifier: License :: OSI Approved :: MIT License
Classifier: Operating System :: OS Independent
Classifier: Programming Language :: Python
Classifier: Programming Language :: Python :: 3
Classifier: Programming Language :: Python :: 3 :: Only
Classifier: Programming Language :: Python :: 3.10
Classifier: Programming Language :: Python :: 3.11
Classifier: Programming Language :: Python :: 3.12
Classifier: Topic :: Internet
Classifier: Topic :: Internet :: WWW/HTTP
Classifier: Topic :: Software Development
Classifier: Topic :: Software Development :: Libraries
Classifier: Topic :: Software Development :: Libraries :: Application Frameworks
Classifier: Topic :: Software Development :: Libraries :: Python Modules
Classifier: Typing :: Typed
Requires-Python: >=3.10
Requires-Dist: beautifulsoup4>=4.12.3
Requires-Dist: markupsafe>=2.0.0
Provides-Extra: full
Requires-Dist: beautifulsoup4>=4.12.3; extra == 'full'
Requires-Dist: watchfiles>=1.0.4; extra == 'full'
Requires-Dist: websockets>=15.0.1; extra == 'full'
Provides-Extra: live-reload
Requires-Dist: watchfiles>=1.0.4; extra == 'live-reload'
Requires-Dist: websockets>=15.0.1; extra == 'live-reload'
